thumb2ISS/__init__.py
thumb2ISS/core.py
thumb2ISS/core_routines.py
thumb2ISS/debugger.py
thumb2ISS/register.py
thumb2ISS/semihosting.py
thumb2ISS/sim.py
thumb2ISS/thumb2ISS.py
thumb2ISS/timings.py
thumb2ISS/version.py
thumb2ISS/instructions/__init__.py
thumb2ISS/instructions/_all.py
thumb2ISS-0.1.1.dist-info/LICENSE
thumb2ISS-0.1.1.dist-info/METADATA
thumb2ISS-0.1.1.dist-info/WHEEL
thumb2ISS-0.1.1.dist-info/entry_points.txt
thumb2ISS-0.1.1.dist-info/top_level.txt
thumb2ISS-0.1.1.dist-info/RECORD
