Metadata-Version: 2.1
Name: thumb2ISS
Version: 0.1.1
Summary: Thumb2 Instruction Set Simulator, allowing to run and debug code compiled for ARM Cortex-M on PC.
License: BSD-3-Clause
Classifier: Development Status :: 3 - Alpha
Classifier: Intended Audience :: Developers
Classifier: License :: OSI Approved :: BSD License
Classifier: Programming Language :: Python :: 3
License-File: LICENSE
Requires-Dist: Click (>=8.0.0)
Requires-Dist: intelhex (>=2.3.0)
